odoo/addons/maintenance_plan_only/README.rst
odoo/addons/maintenance_plan_only/__init__.py
odoo/addons/maintenance_plan_only/__manifest__.py
odoo/addons/maintenance_plan_only/i18n/fr.po
odoo/addons/maintenance_plan_only/i18n/it.po
odoo/addons/maintenance_plan_only/i18n/maintenance_plan_only.pot
odoo/addons/maintenance_plan_only/models/__init__.py
odoo/addons/maintenance_plan_only/models/maintenance_request.py
odoo/addons/maintenance_plan_only/readme/CONTRIBUTORS.md
odoo/addons/maintenance_plan_only/readme/DESCRIPTION.md
odoo/addons/maintenance_plan_only/static/description/icon.png
odoo/addons/maintenance_plan_only/static/description/index.html
odoo/addons/maintenance_plan_only/views/maintenance_request_views.xml
odoo_addon_maintenance_plan_only-18.0.1.0.0.6.dist-info/METADATA
odoo_addon_maintenance_plan_only-18.0.1.0.0.6.dist-info/WHEEL
odoo_addon_maintenance_plan_only-18.0.1.0.0.6.dist-info/top_level.txt
odoo_addon_maintenance_plan_only-18.0.1.0.0.6.dist-info/RECORD
