Metadata-Version: 2.1
Name: odoo-addon-maintenance_plan_only
Version: 18.0.1.0.0.6
Requires-Python: >=3.10
Requires-Dist: odoo-addon-maintenance_plan==18.0.*
Requires-Dist: odoo==18.0.*
Summary: Technical module to hide built-in recurrent settings
Home-page: https://github.com/OCA/maintenance
License: AGPL-3
Author: DEC, Odoo Community Association (OCA)
Author-email: support@odoo-community.org
Classifier: Programming Language :: Python
Classifier: Framework :: Odoo
Classifier: Framework :: Odoo :: 18.0
Classifier: License :: OSI Approved :: GNU Affero General Public License v3
